README.md
setup.py
arara/__init__.py
arara.egg-info/PKG-INFO
arara.egg-info/SOURCES.txt
arara.egg-info/dependency_links.txt
arara.egg-info/requires.txt
arara.egg-info/top_level.txt