Metadata-Version: 1.0
Name: arara
Version: 0.0.0
Summary: holoviews and datashader made easy
Home-page: https://github.com/pedroallenrevez/arara
Author: pedroallenrevez
Author-email: pedroallenrevez@gmail.com
License: NDA
Platform: UNKNOWN
